fastapi_forward/__init__.py
fastapi_forward/decorator.py
fastapi_forward/middleware.py
fastapi_forward-0.0.1.dist-info/METADATA
fastapi_forward-0.0.1.dist-info/WHEEL
fastapi_forward-0.0.1.dist-info/top_level.txt
fastapi_forward-0.0.1.dist-info/RECORD
