Metadata-Version: 2.1
Name: fastapi-forward
Version: 0.0.1
Summary: FastAPI request forwarding middleware
Author-email: Mkdir700 <mkdir700@gmail.com>
License: MIT
Requires-Python: ==3.10.*
Requires-Dist: fastapi
Requires-Dist: httpx>=0.28.0
